kgang/__init__.py
kgang/gangutil.py
kgang-1.0.1.dist-info/LICENSE
kgang-1.0.1.dist-info/METADATA
kgang-1.0.1.dist-info/WHEEL
kgang-1.0.1.dist-info/top_level.txt
kgang-1.0.1.dist-info/RECORD
