Metadata-Version: 2.1
Name: kgang
Version: 1.0.1
License-File: LICENSE
Requires-Dist: requests
Requires-Dist: bs4
Requires-Dist: click
